fasttrack/__init__.py
fasttrack/phase8_rest_apis.py
python_fasttrack-0.1.3.dist-info/METADATA
python_fasttrack-0.1.3.dist-info/WHEEL
python_fasttrack-0.1.3.dist-info/entry_points.txt
python_fasttrack-0.1.3.dist-info/top_level.txt
python_fasttrack-0.1.3.dist-info/RECORD
