Metadata-Version: 2.4
Name: python-fasttrack
Version: 0.1.3
Summary: Phase 8 REST APIs toolkit with CSV/Excel/SQLite export and SpaceX/GitHub demos
Author: Your Name
License: MIT
Keywords: cli,api,requests,pandas,github,spacex,weather
Classifier: Programming Language :: Python :: 3
Classifier: License :: OSI Approved :: MIT License
Classifier: Operating System :: OS Independent
Requires-Python: >=3.9
Requires-Dist: requests>=2.31
Requires-Dist: pandas>=2.0
Requires-Dist: openpyxl>=3.1
Provides-Extra: dotenv
Requires-Dist: python-dotenv>=1.0; extra == "dotenv"
Provides-Extra: cache
Requires-Dist: requests-cache>=1.2; extra == "cache"
